pylnbits/__init__.py
pylnbits/config.py
pylnbits/dj_livestream.py
pylnbits/events.py
pylnbits/lndhub.py
pylnbits/lnurl_p.py
pylnbits/lnurl_w.py
pylnbits/user_manager.py
pylnbits/user_wallet.py
pylnbits/utils.py
tests/__init__.py
tests/test_usermanager.py
tests/test_userwallet.py
pylnbits_lngames-0.0.2.dist-info/LICENSE
pylnbits_lngames-0.0.2.dist-info/METADATA
pylnbits_lngames-0.0.2.dist-info/WHEEL
pylnbits_lngames-0.0.2.dist-info/top_level.txt
pylnbits_lngames-0.0.2.dist-info/RECORD
